woger/__init__.py
woger/action_status.py
woger/action_tracker.py
woger/base_data.py
woger/base_path_structure.py
woger/bind.py
woger/constants.py
woger/data_meta.py
woger/loaders.py
woger/manager.py
woger/path_structure_meta.py
woger/state.py
woger/storage.py
woger/workspace.py
woger-4.1.3.dist-info/DESCRIPTION.rst
woger-4.1.3.dist-info/METADATA
woger-4.1.3.dist-info/RECORD
woger-4.1.3.dist-info/WHEEL
woger-4.1.3.dist-info/metadata.json
woger-4.1.3.dist-info/top_level.txt
