Metadata-Version: 2.0
Name: woger
Version: 4.1.3
Summary: Workspace manager library
Home-page: https://gitlab.com/grihabor/woger
Author: Borodin Gregory
Author-email: grihabor@gmail.com
License: MIT
Keywords: woger workspace manager directory structure version control
Platform: UNKNOWN
Classifier: Development Status :: 3 - Alpha
Classifier: Topic :: Software Development :: Libraries :: Python Modules
Classifier: Intended Audience :: Developers
Classifier: License :: OSI Approved :: MIT License
Classifier: Programming Language :: Python :: 3
Classifier: Programming Language :: Python :: 3.4
Classifier: Programming Language :: Python :: 3.5
Classifier: Programming Language :: Python :: 3.6
